vitool/__init__.py
vitool/ctrl.py
vitool/profiling.py
vitool/rfile.py
vitool/tests.py
vitool-1.0.12.dist-info/LICENSE
vitool-1.0.12.dist-info/METADATA
vitool-1.0.12.dist-info/WHEEL
vitool-1.0.12.dist-info/top_level.txt
vitool-1.0.12.dist-info/RECORD
