Metadata-Version: 2.1
Name: vitool
Version: 1.0.12
Summary: A simple tools.
Home-page: https://github.com/stepvg/vitool
Author: stepvg
Author-email: vyac.st@gmail.com
License: GPLv3
Project-URL: Homepage, https://github.com/stepvg/vitool
Project-URL: Source, https://github.com/stepvg/vitool
Project-URL: Bug Tracker, https://github.com/stepvg/vitool/issues
Project-URL: Documentation, https://github.com/stepvg/vitool#readme
Keywords: vitool,timer,profiling,logging,download,http,file extraction,archives,utils,timeit
Classifier: Programming Language :: Python :: 3
Classifier: License :: OSI Approved :: GNU General Public License v3 (GPLv3)
Classifier: Operating System :: OS Independent
Classifier: Topic :: System :: Monitoring
Classifier: Topic :: Software Development :: Libraries
Classifier: Topic :: Software Development :: Quality Assurance
Classifier: Topic :: Utilities
License-File: LICENSE
Requires-Dist: requests>=2
Requires-Dist: tqdm
